ApiTest365/ApiTest.py
ApiTest365/Api_Save.py
ApiTest365/__init__.py
ApiTest365/test(1).py
ApiTest365/test1.py
Api_Save/ApiTest.py
Api_Save/__init__.py
Winky365/ApiTest.py
Winky365/__init__.py
pyrdt/__init__.py
pyrdt/atom.py
pyrdt/combo.py
pyrdt/math.py
pyrdt/stat.py
pywfz/__init__.py
pywfz/myMath.py
pywfz/sql.py
pywfz/util.py
ApiTest365-1.3.6.dist-info/LICENSE
ApiTest365-1.3.6.dist-info/METADATA
ApiTest365-1.3.6.dist-info/WHEEL
ApiTest365-1.3.6.dist-info/top_level.txt
ApiTest365-1.3.6.dist-info/RECORD
